README.md
aws_ddk/__init__.py
aws_ddk/__main__.py
aws_ddk/__metadata__.py
aws_ddk/commands/__init__.py
aws_ddk/commands/bootstrap.py
aws_ddk/commands/create.py
aws_ddk/commands/deploy.py
aws_ddk/commands/init.py
aws_ddk/data/cloudformation_templates/bootstrap.yaml
aws_ddk/data/project_templates/ddk_app/cookiecutter.json
aws_ddk/data/project_templates/ddk_app/{{cookiecutter.directory_name}}/.gitignore
aws_ddk/data/project_templates/ddk_app/{{cookiecutter.directory_name}}/README.md
aws_ddk/data/project_templates/ddk_app/{{cookiecutter.directory_name}}/app.py
aws_ddk/data/project_templates/ddk_app/{{cookiecutter.directory_name}}/cdk.json
aws_ddk/data/project_templates/ddk_app/{{cookiecutter.directory_name}}/ddk.json
aws_ddk/data/project_templates/ddk_app/{{cookiecutter.directory_name}}/requirements-dev.txt
aws_ddk/data/project_templates/ddk_app/{{cookiecutter.directory_name}}/requirements.txt
aws_ddk/data/project_templates/ddk_app/{{cookiecutter.directory_name}}/setup.py
aws_ddk/data/project_templates/ddk_app/{{cookiecutter.directory_name}}/source.bat
aws_ddk/data/project_templates/ddk_app/{{cookiecutter.directory_name}}/test.sh
aws_ddk/data/project_templates/ddk_app/{{cookiecutter.directory_name}}/{{cookiecutter.package_name}}/__init__.py
aws_ddk/data/project_templates/ddk_app/{{cookiecutter.directory_name}}/{{cookiecutter.package_name}}/{{cookiecutter.stack_file_name}}.py
aws_ddk/exceptions.py
aws_ddk/services/__init__.py
aws_ddk/services/cfn.py
aws_ddk/services/codecommit.py
aws_ddk/sh.py
aws_ddk/utils.py
aws_ddk-0.6.2.dist-info/entry_points.txt
aws_ddk-0.6.2.dist-info/LICENSE
aws_ddk-0.6.2.dist-info/WHEEL
aws_ddk-0.6.2.dist-info/METADATA
aws_ddk-0.6.2.dist-info/RECORD
